dollarN.py
dollarN-1.2.4.dist-info/LICENSE
dollarN-1.2.4.dist-info/METADATA
dollarN-1.2.4.dist-info/WHEEL
dollarN-1.2.4.dist-info/top_level.txt
dollarN-1.2.4.dist-info/RECORD
