Metadata-Version: 2.1
Name: dollarN
Version: 1.2.4
Summary: Implementation of the $N 2D gesture recognizer
Home-page: https://github.com/mikefromlig/dollarN
Author: Michael Ortega
Author-email: michael.ortega@imag.fr
License: UNKNOWN
Platform: UNKNOWN
Classifier: Programming Language :: Python :: 3
Classifier: Operating System :: OS Independent
Requires-Python: >=3.6
Requires-Dist: numpy
